LICENSE
MANIFEST.in
README.md
build_cusig.bat
build_cusig.sh
build_utils.py
requirements.txt
setup.py
avx_info/avx_info.cpp
docs/Doxyfile
docs/Makefile
docs/conf.py
docs/index.rst
docs/make.bat
docs/requirements.in
docs/requirements.txt
docs/sphinx-build.pclprof
docs/_static/custom_tree.css
docs/_static/logo_dark.png
docs/_static/logo_light.png
docs/pages/backprop.rst
docs/pages/conventions.rst
docs/pages/cpp.rst
docs/pages/installation.rst
docs/pages/log_signatures.rst
docs/pages/path_transformations.rst
docs/pages/signature_kernels.rst
docs/pages/signatures.rst
docs/pages/torch_api.rst
docs/pages/backprop/sig_backprop.rst
docs/pages/backprop/sig_combine_backprop.rst
docs/pages/backprop/sig_kernel_backprop.rst
docs/pages/backprop/sig_kernel_gram_backprop.rst
docs/pages/backprop/sig_to_log_sig_backprop.rst
docs/pages/backprop/transform_path_backprop.rst
docs/pages/cpp/cpsig.rst
docs/pages/cpp/cusig.rst
docs/pages/cpp/cpsig/cp_log_sig.rst
docs/pages/cpp/cpsig/cp_sig_combine.rst
docs/pages/cpp/cpsig/cp_sig_kernel.rst
docs/pages/cpp/cpsig/cp_sig_length.rst
docs/pages/cpp/cpsig/cp_signature.rst
docs/pages/cpp/cpsig/cp_transform_path.rst
docs/pages/cpp/cusig/cu_sig_kernel.rst
docs/pages/cpp/cusig/cu_transform_path.rst
docs/pages/log_signatures/clear_cache.rst
docs/pages/log_signatures/log_sig.rst
docs/pages/log_signatures/log_sig_length.rst
docs/pages/log_signatures/log_sig_methods.rst
docs/pages/log_signatures/prepare_log_sig.rst
docs/pages/log_signatures/set_cache_dir.rst
docs/pages/log_signatures/sig_to_log_sig.rst
docs/pages/path_transformations/transform_path.rst
docs/pages/signature_kernels/expected_sig_score.rst
docs/pages/signature_kernels/sig_kernel.rst
docs/pages/signature_kernels/sig_kernel_gram.rst
docs/pages/signature_kernels/sig_mmd.rst
docs/pages/signature_kernels/sig_score.rst
docs/pages/signature_kernels/static_kernels.rst
docs/pages/signatures/sig.rst
docs/pages/signatures/sig_combine.rst
docs/pages/signatures/sig_length.rst
pysiglib/README.md
pysiglib.egg-info/PKG-INFO
pysiglib.egg-info/SOURCES.txt
pysiglib.egg-info/dependency_links.txt
pysiglib.egg-info/requires.txt
pysiglib.egg-info/top_level.txt
